ACETH/__init__.py
ACETH/chatbot.py
ACETH/data/emoji_model.h5
ACETH/data/encoder_emoji.pkl
ACETH/data/token_emoji.pkl
ACETH-0.0.12.dist-info/LICENSE.txt
ACETH-0.0.12.dist-info/METADATA
ACETH-0.0.12.dist-info/WHEEL
ACETH-0.0.12.dist-info/top_level.txt
ACETH-0.0.12.dist-info/RECORD
