Metadata-Version: 2.1
Name: ACETH
Version: 0.0.12
Summary: Analytics Club ETHZ helper package
Home-page: https://github.com/kimo26/ACE
Author: Karim Galal, Walid Chatt
Author-email: karim.galal@analytics-club.org, walid.chatt@analytics-club.org
License: MIT
Keywords: ETHZ,Analytics Club,AI,Artificial intelligence,Machine Learning,Data processing,Chatbot,Education,ML
Classifier: Programming Language :: Python :: 3
License-File: LICENSE.txt
Requires-Dist: numpy
Requires-Dist: pandas
Requires-Dist: torch
Requires-Dist: tensorflow
Requires-Dist: transformers
Requires-Dist: sklearn
Requires-Dist: emoji
Requires-Dist: accelerate
Requires-Dist: bitsandbytes
Requires-Dist: scikit-learn
